dyslexicloglog/Autocorrector.py
dyslexicloglog/Hasher.py
dyslexicloglog/HyperLogLog.py
dyslexicloglog/__init__.py
dyslexicloglog/compare.py
dyslexicloglog/compare3.py
dyslexicloglog/test_files/20k_shun4midx.txt
dyslexicloglog/test_files/database.txt
dyslexicloglog/test_files/texting.txt
dyslexicloglog-2.0.2.dist-info/METADATA
dyslexicloglog-2.0.2.dist-info/WHEEL
dyslexicloglog-2.0.2.dist-info/licenses/LICENSE
dyslexicloglog-2.0.2.dist-info/RECORD
