Metadata-Version: 2.4
Name: DyslexicLogLog
Version: 2.0.2
Summary: A Frequency-Quantized HyperLogLog Autocorrection algorithm that also is dyslexia-friendly.
Project-URL: Homepage, https://github.com/shun4midx/FQ-HyperLogLog-Autocorrect
Project-URL: Issues, https://github.com/shun4midx/FQ-HyperLogLog-Autocorrect/issues
Author-email: Shun/翔海 <shun4midx@gmail.com>
License-Expression: MIT
License-File: LICENSE
Classifier: Operating System :: OS Independent
Requires-Python: >=3.9
Requires-Dist: bitarray>=3.5.1
